{"is_source_file": true, "format": "js", "description": ".js file: tailwind.config.js", "external_files": [], "external_methods": [], "published": [], "classes": [], "methods": [], "calls": [], "search-terms": ["tailwind.config.js", "js"], "state": 2, "file_id": 13, "knowledge_revision": 52, "git_revision": "194bbccc42f61bde3190652e421791a9f76d8a6a", "revision_history": [{"27": ""}, {"52": "194bbccc42f61bde3190652e421791a9f76d8a6a"}], "ctags": [], "filename": "lms_frontend/tailwind.config.js", "format-version": 4, "code-base-name": "https://github.com/kavia-common/learner-pathway-lms-252592-253067.git:kavia-main"}